nitro/__init__.py
nitro/core.py
nitro/llm.py
nitro/llm_config.yaml.sample
nitro/logger.py
nitro/logging.py
nitrotools-0.2.0.dist-info/METADATA
nitrotools-0.2.0.dist-info/WHEEL
nitrotools-0.2.0.dist-info/licenses/LICENSE
nitrotools-0.2.0.dist-info/RECORD
